pchru
