Metadata-Version: 2.1
Name: pchru
Version: 0.0.2
Summary: Generate a hash of the provided dictionary
Home-page: UNKNOWN
Author-email: sagrutyanin4@gmail.com
License: UNKNOWN
Platform: UNKNOWN
